rtl/flag_unit.v

// Status flag generation: Zero, Carry, Overflow, Negative

module flag_unit #(
    parameter WIDTH = 4
)(
    input  [WIDTH-1:0] result,
    input  carry_in,
    input  overflow_in,
    input  is_arithmetic,    // 1 if arithmetic op, 0 if logic op
    output zero,
    output carry,
    output overflow,
    output negative
);

    // Zero flag: result is all zeros
    assign zero = (result == {WIDTH{1'b0}});
    
    // Negative flag: MSB of result (sign bit in two's complement)
    assign negative = result[WIDTH-1];
    
    // Carry and Overflow only valid for arithmetic operations
    assign carry = is_arithmetic ? carry_in : 1'b0;
    assign overflow = is_arithmetic ? overflow_in : 1'b0;

endmodule

rtl/logic_unit.v

// Bitwise logical operations: AND, OR, XOR, NOT

module logic_unit #(
    parameter WIDTH = 4
)(
    input  [WIDTH-1:0] a,
    input  [WIDTH-1:0] b,
    input  [1:0] op,        // 00=AND, 01=OR, 10=XOR, 11=NOT
    output [WIDTH-1:0] result
);

    reg [WIDTH-1:0] logic_result;
    
    always @(*) begin
        case (op)
            2'b00:   logic_result = a & b;   // AND
            2'b01:   logic_result = a | b;   // OR
            2'b10:   logic_result = a ^ b;   // XOR
            2'b11:   logic_result = ~a;      // NOT
            default: logic_result = {WIDTH{1'b0}};
        endcase
    end
    
    assign result = logic_result;

endmodule

rtl/arithmetic_core.v

// Arithmetic operations: ADD, SUB, INC, DEC, CMP
// Generates carry and overflow flags

module arithmetic_core #(
    parameter WIDTH = 4
)(
    input  [WIDTH-1:0] a,
    input  [WIDTH-1:0] b,
    input  [1:0] op,        // 00=ADD, 01=SUB, 10=INC, 11=DEC
    output [WIDTH-1:0] result,
    output carry_out,
    output overflow
);

    reg [WIDTH:0] temp_result;
    reg c_out, v_out;
    
    always @(*) begin
        case (op)
            2'b00: begin  // ADD
                temp_result = {1'b0, a} + {1'b0, b};
                c_out = temp_result[WIDTH];
                v_out = (a[WIDTH-1] == b[WIDTH-1]) && (a[WIDTH-1] != temp_result[WIDTH-1]);
            end
            2'b01: begin  // SUB
                temp_result = {1'b0, a} - {1'b0, b};
                c_out = temp_result[WIDTH];  // Borrow
                v_out = (a[WIDTH-1] != b[WIDTH-1]) && (a[WIDTH-1] != temp_result[WIDTH-1]);
            end
            2'b10: begin  // INC
                temp_result = {1'b0, a} + 1'b1;
                c_out = temp_result[WIDTH];
                v_out = (a == {1'b0, {(WIDTH-1){1'b1}}});  // 0111 -> 1000 overflow
            end
            2'b11: begin  // DEC
                temp_result = {1'b0, a} - 1'b1;
                c_out = temp_result[WIDTH];
                v_out = (a == {1'b1, {(WIDTH-1){1'b0}}});  // 1000 -> 0111 overflow
            end
        endcase
    end
    
    assign result = temp_result[WIDTH-1:0];
    assign carry_out = c_out;
    assign overflow = v_out;

endmodule

rtl/alu_4bit.v

// Top-level 4-bit ALU module
// Opcode map:
// 000 - ADD    (arithmetic)
// 001 - SUB    (arithmetic)
// 010 - INC    (arithmetic)
// 011 - DEC    (arithmetic)
// 100 - AND    (logic)
// 101 - OR     (logic)
// 110 - XOR    (logic)
// 111 - NOT    (logic)

module alu_4bit #(
    parameter WIDTH = 4
)(
    input  [WIDTH-1:0] A,
    input  [WIDTH-1:0] B,
    input  [2:0] opcode,
    output [WIDTH-1:0] result,
    output zero,
    output carry,
    output overflow,
    output negative
);

    wire [WIDTH-1:0] arith_result;
    wire [WIDTH-1:0] logic_result;
    wire arith_carry;
    wire arith_overflow;
    wire is_arithmetic;
    wire [WIDTH-1:0] final_result;
    
    // Determine if operation is arithmetic (opcode[2] == 0) or logic (opcode[2] == 1)
    assign is_arithmetic = ~opcode[2];
    
    // Instantiate arithmetic core
    arithmetic_core #(.WIDTH(WIDTH)) arith_core (
        .a(A),
        .b(B),
        .op(opcode[1:0]),
        .result(arith_result),
        .carry_out(arith_carry),
        .overflow(arith_overflow)
    );
    
    // Instantiate logic unit
    logic_unit #(.WIDTH(WIDTH)) logic_core (
        .a(A),
        .b(B),
        .op(opcode[1:0]),
        .result(logic_result)
    );
    
    // Result multiplexer: select arithmetic or logic result
    assign final_result = is_arithmetic ? arith_result : logic_result;
    
    // Instantiate flag unit
    flag_unit #(.WIDTH(WIDTH)) flags (
        .result(final_result),
        .carry_in(arith_carry),
        .overflow_in(arith_overflow),
        .is_arithmetic(is_arithmetic),
        .zero(zero),
        .carry(carry),
        .overflow(overflow),
        .negative(negative)
    );
    
    assign result = final_result;

endmodule

tb/tb_alu_4bit.v
// tb_alu_4bit.v
// Comprehensive testbench with directed and randomized tests

`timescale 1ns/1ps

module tb_alu_4bit;
    parameter WIDTH = 4;
    
    reg [WIDTH-1:0] A, B;
    reg [2:0] opcode;
    wire [WIDTH-1:0] result;
    wire zero, carry, overflow, negative;
    
    integer i, errors;
    
    // Instantiate the ALU
    alu_4bit #(.WIDTH(WIDTH)) dut (
        .A(A),
        .B(B),
        .opcode(opcode),
        .result(result),
        .zero(zero),
        .carry(carry),
        .overflow(overflow),
        .negative(negative)
    );
    
    // VCD dump for GTKWave
    initial begin
        $dumpfile("alu_4bit.vcd");
        $dumpvars(0, tb_alu_4bit);
    end
    
    // Test task
    task test_alu;
        input [WIDTH-1:0] a_val, b_val;
        input [2:0] op;
        input [WIDTH-1:0] expected_result;
        input expected_z, expected_c, expected_v, expected_n;
        begin
            A = a_val;
            B = b_val;
            opcode = op;
            #10;
            
            if (result !== expected_result || 
                zero !== expected_z || 
                carry !== expected_c || 
                overflow !== expected_v || 
                negative !== expected_n) begin
                $display("ERROR at time %0t:", $time);
                $display("  A=%b, B=%b, opcode=%b", A, B, opcode);
                $display("  Expected: result=%b Z=%b C=%b V=%b N=%b", 
                         expected_result, expected_z, expected_c, expected_v, expected_n);
                $display("  Got:      result=%b Z=%b C=%b V=%b N=%b", 
                         result, zero, carry, overflow, negative);
                errors = errors + 1;
            end else begin
                $display("PASS: A=%b, B=%b, op=%b -> result=%b Z=%b C=%b V=%b N=%b",
                         A, B, opcode, result, zero, carry, overflow, negative);
            end
        end
    endtask
    
    initial begin
        errors = 0;
        $display("\n=== Starting ALU Testbench ===\n");
        
        // ===== DIRECTED TESTS =====
        $display("--- Arithmetic Tests ---");
        
        // ADD tests
        $display("Testing ADD...");
        test_alu(4'd3, 4'd2, 3'b000, 4'd5, 0, 0, 0, 0);     // 3+2=5
        test_alu(4'd7, 4'd1, 3'b000, 4'd8, 0, 0, 1, 1);     // Overflow: 7+1=8 (0111+0001=1000)
        test_alu(4'd15, 4'd1, 3'b000, 4'd0, 1, 1, 0, 0);    // Carry: 15+1=16 (overflow to 0)
        test_alu(4'd0, 4'd0, 3'b000, 4'd0, 1, 0, 0, 0);     // Zero flag
        test_alu(4'd8, 4'd8, 3'b000, 4'd0, 1, 1, 1, 0);     // -8+(-8)=0 with carry and overflow
        
        // SUB tests
        $display("Testing SUB...");
        test_alu(4'd5, 4'd3, 3'b001, 4'd2, 0, 0, 0, 0);     // 5-3=2
        test_alu(4'd3, 4'd5, 3'b001, 4'd14, 0, 1, 0, 1);    // 3-5=-2 (borrow)
        test_alu(4'd8, 4'd1, 3'b001, 4'd7, 0, 0, 1, 0);     // Overflow: -8-1=7 (1000-0001=0111)
        test_alu(4'd0, 4'd0, 3'b001, 4'd0, 1, 0, 0, 0);     // Zero flag
        test_alu(4'd7, 4'd8, 3'b001, 4'd15, 0, 1, 1, 1);    // 7-(-8)=-1 with overflow
        
        // INC tests
        $display("Testing INC...");
        test_alu(4'd5, 4'd0, 3'b010, 4'd6, 0, 0, 0, 0);     // 5+1=6
        test_alu(4'd7, 4'd0, 3'b010, 4'd8, 0, 0, 1, 1);     // Overflow: 7+1=8
        test_alu(4'd15, 4'd0, 3'b010, 4'd0, 1, 1, 0, 0);    // 15+1=0 with carry
        
        // DEC tests
        $display("Testing DEC...");
        test_alu(4'd5, 4'd0, 3'b011, 4'd4, 0, 0, 0, 0);     // 5-1=4
        test_alu(4'd8, 4'd0, 3'b011, 4'd7, 0, 0, 1, 0);     // Overflow: -8-1=7
        test_alu(4'd0, 4'd0, 3'b011, 4'd15, 0, 1, 0, 1);    // 0-1=-1 (borrow)
        
        // ===== LOGIC TESTS =====
        $display("\n--- Logic Tests ---");
        
        // AND tests
        $display("Testing AND...");
        test_alu(4'b1010, 4'b1100, 3'b100, 4'b1000, 0, 0, 0, 1);
        test_alu(4'b1111, 4'b1111, 3'b100, 4'b1111, 0, 0, 0, 1);
        test_alu(4'b1010, 4'b0101, 3'b100, 4'b0000, 1, 0, 0, 0);  // Zero flag
        
        // OR tests
        $display("Testing OR...");
        test_alu(4'b1010, 4'b0101, 3'b101, 4'b1111, 0, 0, 0, 1);
        test_alu(4'b0000, 4'b0000, 3'b101, 4'b0000, 1, 0, 0, 0);  // Zero flag
        test_alu(4'b1100, 4'b0011, 3'b101, 4'b1111, 0, 0, 0, 1);
        
        // XOR tests
        $display("Testing XOR...");
        test_alu(4'b1010, 4'b1100, 3'b110, 4'b0110, 0, 0, 0, 0);
        test_alu(4'b1111, 4'b1111, 3'b110, 4'b0000, 1, 0, 0, 0);  // Zero flag
        test_alu(4'b1010, 4'b0101, 3'b110, 4'b1111, 0, 0, 0, 1);
        
        // NOT tests
        $display("Testing NOT...");
        test_alu(4'b1010, 4'b0000, 3'b111, 4'b0101, 0, 0, 0, 0);
        test_alu(4'b0000, 4'b0000, 3'b111, 4'b1111, 0, 0, 0, 1);
        test_alu(4'b1111, 4'b0000, 3'b111, 4'b0000, 1, 0, 0, 0);  // Zero flag
        
        // ===== RANDOMIZED TESTS =====
        $display("\n--- Randomized Tests ---");
        for (i = 0; i < 50; i = i + 1) begin
            A = $random;
            B = $random;
            opcode = $random % 8;
            #10;
            // Just display random test results without checking
            // (in real testbench, you'd compute expected values)
            $display("Random test %0d: A=%b, B=%b, op=%b -> result=%b flags=Z%bC%bV%bN%b",
                     i, A, B, opcode, result, zero, carry, overflow, negative);
        end
        
        // ===== TEST SUMMARY =====
        $display("\n=== Test Summary ===");
        if (errors == 0) begin
            $display("ALL TESTS PASSED!");
        end else begin
            $display("TESTS FAILED: %0d errors", errors);
        end
        
        $display("\nSimulation complete. Check alu_4bit.vcd with GTKWave.");
        #50;
        $finish;
    end

endmodule

sim/alu_4bit.vcd
$date
	Thu Oct 30 19:33:45 2025
$end
$version
	Icarus Verilog
$end
$timescale
	1ps
$end
$scope module tb_alu_4bit $end
$var wire 1 ! zero $end
$var wire 4 " result [3:0] $end
$var wire 1 # overflow $end
$var wire 1 $ negative $end
$var wire 1 % carry $end
$var parameter 32 & WIDTH $end
$var reg 4 ' A [3:0] $end
$var reg 4 ( B [3:0] $end
$var reg 3 ) opcode [2:0] $end
$var integer 32 * errors [31:0] $end
$var integer 32 + i [31:0] $end
$scope module dut $end
$var wire 4 , A [3:0] $end
$var wire 4 - B [3:0] $end
$var wire 1 . is_arithmetic $end
$var wire 3 / opcode [2:0] $end
$var wire 4 0 result [3:0] $end
$var wire 1 ! zero $end
$var wire 1 # overflow $end
$var wire 1 $ negative $end
$var wire 4 1 logic_result [3:0] $end
$var wire 4 2 final_result [3:0] $end
$var wire 1 % carry $end
$var wire 4 3 arith_result [3:0] $end
$var wire 1 4 arith_overflow $end
$var wire 1 5 arith_carry $end
$var parameter 32 6 WIDTH $end
$scope module arith_core $end
$var wire 4 7 a [3:0] $end
$var wire 4 8 b [3:0] $end
$var wire 1 5 carry_out $end
$var wire 2 9 op [1:0] $end
$var wire 4 : result [3:0] $end
$var wire 1 4 overflow $end
$var parameter 32 ; WIDTH $end
$var reg 1 5 c_out $end
$var reg 5 < temp_result [4:0] $end
$var reg 1 4 v_out $end
$upscope $end
$scope module flags $end
$var wire 1 5 carry_in $end
$var wire 1 . is_arithmetic $end
$var wire 1 4 overflow_in $end
$var wire 4 = result [3:0] $end
$var wire 1 ! zero $end
$var wire 1 # overflow $end
$var wire 1 $ negative $end
$var wire 1 % carry $end
$var parameter 32 > WIDTH $end
$upscope $end
$scope module logic_core $end
$var wire 4 ? a [3:0] $end
$var wire 4 @ b [3:0] $end
$var wire 2 A op [1:0] $end
$var wire 4 B result [3:0] $end
$var parameter 32 C WIDTH $end
$var reg 4 D logic_result [3:0] $end
$upscope $end
$upscope $end
$scope task test_alu $end
$var reg 4 E a_val [3:0] $end
$var reg 4 F b_val [3:0] $end
$var reg 1 G expected_c $end
$var reg 1 H expected_n $end
$var reg 4 I expected_result [3:0] $end
$var reg 1 J expected_v $end
$var reg 1 K expected_z $end
$var reg 3 L op [2:0] $end
$upscope $end
$upscope $end
$enddefinitions $end
$comment Show the parameter values. $end
$dumpall
b100 C
b100 >
b100 ;
b100 6
b100 &
$end
#0
$dumpvars
b0 L
0K
0J
b101 I
0H
0G
b10 F
b11 E
b10 D
b10 B
b0 A
b10 @
b11 ?
b101 =
b101 <
b101 :
b0 9
b10 8
b11 7
05
04
b101 3
b101 2
b10 1
b101 0
b0 /
1.
b10 -
b11 ,
bx +
b0 *
b0 )
b10 (
b11 '
0%
0$
0#
b101 "
0!
$end
#10000
1$
b1000 "
b1000 0
b1000 2
b1000 =
1#
b1000 3
b1000 :
14
b1000 <
b1 1
b1 B
b1 D
b1 (
b1 -
b1 8
b1 @
b111 '
b111 ,
b111 7
b111 ?
1H
1J
b1000 I
b1 F
b111 E
#20000
0$
1!
b0 "
b0 0
b0 2
b0 =
0#
1%
b0 3
b0 :
04
15
b10000 <
b1111 '
b1111 ,
b1111 7
b1111 ?
0H
0J
1G
1K
b0 I
b1111 E
#30000
0%
05
b0 <
b0 1
b0 B
b0 D
b0 (
b0 -
b0 8
b0 @
b0 '
b0 ,
b0 7
b0 ?
0G
b0 F
b0 E
#40000
1#
1%
14
15
b10000 <
b1000 1
b1000 B
b1000 D
b1000 (
b1000 -
b1000 8
b1000 @
b1000 '
b1000 ,
b1000 7
b1000 ?
1J
1G
b1000 F
b1000 E
#50000
0$
0#
0!
b10 "
b10 0
b10 2
b10 =
04
0%
b10 3
b10 :
b1 9
b1 A
05
b10 <
b111 1
b111 B
b111 D
b1 )
b1 /
b11 (
b11 -
b11 8
b11 @
b101 '
b101 ,
b101 7
b101 ?
0J
0G
0K
b10 I
b1 L
b11 F
b101 E
#60000
1$
b1110 "
b1110 0
b1110 2
b1110 =
1%
b1110 3
b1110 :
15
b11110 <
b101 (
b101 -
b101 8
b101 @
b11 '
b11 ,
b11 7
b11 ?
1H
1G
b1110 I
b101 F
b11 E
#70000
0$
b111 "
b111 0
b111 2
b111 =
1#
0%
b111 3
b111 :
14
05
b111 <
b1001 1
b1001 B
b1001 D
b1 (
b1 -
b1 8
b1 @
b1000 '
b1000 ,
b1000 7
b1000 ?
0H
1J
0G
b111 I
b1 F
b1000 E
#80000
1!
b0 "
b0 0
b0 2
b0 =
0#
b0 3
b0 :
04
b0 <
b0 1
b0 B
b0 D
b0 (
b0 -
b0 8
b0 @
b0 '
b0 ,
b0 7
b0 ?
0J
1K
b0 I
b0 F
b0 E
#90000
1$
0!
b1111 "
b1111 0
b1111 2
b1111 =
1#
1%
b1111 3
b1111 :
14
15
b11111 <
b1111 1
b1111 B
b1111 D
b1000 (
b1000 -
b1000 8
b1000 @
b111 '
b111 ,
b111 7
b111 ?
1H
1J
1G
0K
b1111 I
b1000 F
b111 E
#100000
0$
b110 "
b110 0
b110 2
b110 =
0#
0%
b110 3
b110 :
b10 9
b10 A
04
05
b110 <
b101 1
b101 B
b101 D
b10 )
b10 /
b0 (
b0 -
b0 8
b0 @
b101 '
b101 ,
b101 7
b101 ?
0H
0J
0G
b110 I
b10 L
b0 F
b101 E
#110000
1$
b1000 "
b1000 0
b1000 2
b1000 =
1#
b1000 3
b1000 :
14
b1000 <
b111 1
b111 B
b111 D
b111 '
b111 ,
b111 7
b111 ?
1H
1J
b1000 I
b111 E
#120000
0$
1!
b0 "
b0 0
b0 2
b0 =
0#
1%
b0 3
b0 :
04
15
b10000 <
b1111 1
b1111 B
b1111 D
b1111 '
b1111 ,
b1111 7
b1111 ?
0H
0J
1G
1K
b0 I
b1111 E
#130000
0!
b100 "
b100 0
b100 2
b100 =
0%
b100 3
b100 :
b11 9
b11 A
05
b100 <
b1010 1
b1010 B
b1010 D
b11 )
b11 /
b101 '
b101 ,
b101 7
b101 ?
0G
0K
b100 I
b11 L
b101 E
#140000
b111 "
b111 0
b111 2
b111 =
1#
b111 3
b111 :
14
b111 <
b111 1
b111 B
b111 D
b1000 '
b1000 ,
b1000 7
b1000 ?
1J
b111 I
b1000 E
#150000
1$
b1111 "
b1111 0
b1111 2
b1111 =
0#
1%
b1111 3
b1111 :
04
15
b11111 <
b1111 1
b1111 B
b1111 D
b0 '
b0 ,
b0 7
b0 ?
1H
0J
1G
b1111 I
b0 E
#160000
b1000 "
b1000 0
b1000 2
b1000 =
0.
14
0%
b110 3
b110 :
b0 9
b0 A
15
b10110 <
b1000 1
b1000 B
b1000 D
b100 )
b100 /
b1100 (
b1100 -
b1100 8
b1100 @
b1010 '
b1010 ,
b1010 7
b1010 ?
0G
b1000 I
b100 L
b1100 F
b1010 E
#170000
b1110 3
b1110 :
b1111 "
b1111 0
b1111 2
b1111 =
04
b11110 <
b1111 1
b1111 B
b1111 D
b1111 (
b1111 -
b1111 8
b1111 @
b1111 '
b1111 ,
b1111 7
b1111 ?
b1111 I
b1111 F
b1111 E
#180000
0$
b1111 3
b1111 :
1!
b0 "
b0 0
b0 2
b0 =
05
b1111 <
b0 1
b0 B
b0 D
b101 (
b101 -
b101 8
b101 @
b1010 '
b1010 ,
b1010 7
b1010 ?
0H
1K
b0 I
b101 F
b1010 E
#190000
1$
b101 3
b101 :
0!
b1111 "
b1111 0
b1111 2
b1111 =
14
b101 <
b1111 1
b1111 B
b1111 D
b1 9
b1 A
b101 )
b101 /
1H
0K
b1111 I
b101 L
#200000
0$
b0 3
b0 :
1!
b0 "
b0 0
b0 2
b0 =
04
b0 <
b0 1
b0 B
b0 D
b0 (
b0 -
b0 8
b0 @
b0 '
b0 ,
b0 7
b0 ?
0H
1K
b0 I
b0 F
b0 E
#210000
1$
b1001 3
b1001 :
0!
b1111 "
b1111 0
b1111 2
b1111 =
b1001 <
b1111 1
b1111 B
b1111 D
b11 (
b11 -
b11 8
b11 @
b1100 '
b1100 ,
b1100 7
b1100 ?
1H
0K
b1111 I
b11 F
b1100 E
#220000
0$
b1011 3
b1011 :
b110 "
b110 0
b110 2
b110 =
b10 9
b10 A
05
b1011 <
b110 1
b110 B
b110 D
b110 )
b110 /
b1100 (
b1100 -
b1100 8
b1100 @
b1010 '
b1010 ,
b1010 7
b1010 ?
0H
b110 I
b110 L
b1100 F
b1010 E
#230000
b0 3
b0 :
1!
b0 "
b0 0
b0 2
b0 =
15
b10000 <
b0 1
b0 B
b0 D
b1111 (
b1111 -
b1111 8
b1111 @
b1111 '
b1111 ,
b1111 7
b1111 ?
1K
b0 I
b1111 F
b1111 E
#240000
1$
b1011 3
b1011 :
0!
b1111 "
b1111 0
b1111 2
b1111 =
05
b1011 <
b1111 1
b1111 B
b1111 D
b101 (
b101 -
b101 8
b101 @
b1010 '
b1010 ,
b1010 7
b1010 ?
1H
0K
b1111 I
b101 F
b1010 E
#250000
0$
b1001 3
b1001 :
b1001 <
b101 "
b101 0
b101 2
b101 =
b11 9
b11 A
b101 1
b101 B
b101 D
b111 )
b111 /
b0 (
b0 -
b0 8
b0 @
0H
b101 I
b111 L
b0 F
#260000
1$
b1111 3
b1111 :
b1111 "
b1111 0
b1111 2
b1111 =
15
b11111 <
b1111 1
b1111 B
b1111 D
b0 '
b0 ,
b0 7
b0 ?
1H
b1111 I
b0 E
#270000
0$
b1110 3
b1110 :
1!
b0 "
b0 0
b0 2
b0 =
05
b1110 <
b0 1
b0 B
b0 D
b1111 '
b1111 ,
b1111 7
b1111 ?
0H
1K
b0 I
b1111 E
#280000
0$
1.
b11 3
b11 :
0!
b11 "
b11 0
b11 2
b11 =
b1 9
b1 A
b11 <
b101 1
b101 B
b101 D
b1 )
b1 /
b1 (
b1 -
b1 8
b1 @
b100 '
b100 ,
b100 7
b100 ?
b0 +
#290000
1$
b1111 "
b1111 0
b1111 2
b1111 =
0.
0%
b110 3
b110 :
15
b10110 <
b1111 1
b1111 B
b1111 D
b101 )
b101 /
b1101 (
b1101 -
b1101 8
b1101 @
b11 '
b11 ,
b11 7
b11 ?
b1 +
#300000
0$
1.
b11 3
b11 :
b11 "
b11 0
b11 2
b11 =
05
b11 <
b111 1
b111 B
b111 D
b1 )
b1 /
b10 (
b10 -
b10 8
b10 @
b101 '
b101 ,
b101 7
b101 ?
b10 +
#310000
1$
b1111 "
b1111 0
b1111 2
b1111 =
0.
0#
b111 3
b111 :
14
b111 <
b1111 1
b1111 B
b1111 D
b101 )
b101 /
b110 (
b110 -
b110 8
b110 @
b1101 '
b1101 ,
b1101 7
b1101 ?
b11 +
#320000
0$
1.
b1 3
b1 :
b1 "
b1 0
b1 2
b1 =
04
b1 <
b1101 1
b1101 B
b1101 D
b1 )
b1 /
b1100 (
b1100 -
b1100 8
b1100 @
b100 +
#330000
b111 "
b111 0
b111 2
b111 =
b111 3
b111 :
b111 <
b10 9
b10 A
b11 1
b11 B
b11 D
b10 )
b10 /
b101 (
b101 -
b101 8
b101 @
b110 '
b110 ,
b110 7
b110 ?
b101 +
#340000
b110 "
b110 0
b110 2
b110 =
b110 3
b110 :
b110 <
b10 1
b10 B
b10 D
b111 (
b111 -
b111 8
b111 @
b101 '
b101 ,
b101 7
b101 ?
b110 +
#350000
1$
b1101 "
b1101 0
b1101 2
b1101 =
0.
0%
b0 3
b0 :
15
b10000 <
b1101 1
b1101 B
b1101 D
b110 )
b110 /
b10 (
b10 -
b10 8
b10 @
b1111 '
b1111 ,
b1111 7
b1111 ?
b111 +
#360000
0$
1!
b0 "
b0 0
b0 2
b0 =
b0 1
b0 B
b0 D
b1101 3
b1101 :
b0 9
b0 A
05
b1101 <
b100 )
b100 /
b101 (
b101 -
b101 8
b101 @
b1000 '
b1000 ,
b1000 7
b1000 ?
b1000 +
#370000
1$
b0 3
b0 :
0!
b1101 "
b1101 0
b1101 2
b1101 =
b1 9
b1 A
05
b0 <
b1101 1
b1101 B
b1101 D
b101 )
b101 /
b1101 (
b1101 -
b1101 8
b1101 @
b1101 '
b1101 ,
b1101 7
b1101 ?
b1001 +
#380000
1.
b1101 3
b1101 :
b1101 "
b1101 0
b1101 2
b1101 =
b0 9
b0 A
04
05
b1101 <
b10 1
b10 B
b10 D
b0 )
b0 /
b1010 (
b1010 -
b1010 8
b1010 @
b11 '
b11 ,
b11 7
b11 ?
b1010 +
#390000
b1010 "
b1010 0
b1010 2
b1010 =
0.
15
b110 3
b110 :
b1 9
b1 A
b10110 <
b1010 1
b1010 B
b1010 D
b101 )
b101 /
b0 '
b0 ,
b0 7
b0 ?
b1011 +
#400000
0$
b11 3
b11 :
b111 "
b111 0
b111 2
b111 =
05
b11 <
b111 1
b111 B
b111 D
b11 (
b11 -
b11 8
b11 @
b110 '
b110 ,
b110 7
b110 ?
b1100 +
#410000
1$
b1000 3
b1000 :
b1011 "
b1011 0
b1011 2
b1011 =
14
15
b11000 <
b1011 1
b1011 B
b1011 D
b1011 (
b1011 -
b1011 8
b1011 @
b11 '
b11 ,
b11 7
b11 ?
b1101 +
#420000
b100 3
b100 :
b1110 "
b1110 0
b1110 2
b1110 =
04
b10100 <
b1110 1
b1110 B
b1110 D
b1110 (
b1110 -
b1110 8
b1110 @
b10 '
b10 ,
b10 7
b10 ?
b1110 +
#430000
0$
1!
1%
1.
b0 3
b0 :
b0 "
b0 0
b0 2
b0 =
b10 9
b10 A
15
b10000 <
b1100 1
b1100 B
b1100 D
b10 )
b10 /
b11 (
b11 -
b11 8
b11 @
b1111 '
b1111 ,
b1111 7
b1111 ?
b1111 +
#440000
1$
0!
b1011 "
b1011 0
b1011 2
b1011 =
0%
b1011 3
b1011 :
05
b1011 <
b110 1
b110 B
b110 D
b1100 (
b1100 -
b1100 8
b1100 @
b1010 '
b1010 ,
b1010 7
b1010 ?
b10000 +
#450000
b0 9
b0 A
b0 1
b0 B
b0 D
b0 )
b0 /
b1 (
b1 -
b1 8
b1 @
b10001 +
#460000
0$
b111 "
b111 0
b111 2
b111 =
1#
0%
b111 3
b111 :
b11 9
b11 A
14
05
b111 <
b111 1
b111 B
b111 D
b11 )
b11 /
b1001 (
b1001 -
b1001 8
b1001 @
b1000 '
b1000 ,
b1000 7
b1000 ?
b10010 +
#470000
1!
b0 "
b0 0
b0 2
b0 =
0.
0#
b111 3
b111 :
b10 9
b10 A
04
b111 <
b0 1
b0 B
b0 D
b110 )
b110 /
b110 (
b110 -
b110 8
b110 @
b110 '
b110 ,
b110 7
b110 ?
b10011 +
#480000
1$
1.
b1011 3
b1011 :
0!
b1011 "
b1011 0
b1011 2
b1011 =
b11 9
b11 A
b1011 <
b11 1
b11 B
b11 D
b11 )
b11 /
b1010 (
b1010 -
b1010 8
b1010 @
b1100 '
b1100 ,
b1100 7
b1100 ?
b10100 +
#490000
b1110 "
b1110 0
b1110 2
b1110 =
0.
b0 3
b0 :
b0 <
b1110 1
b1110 B
b1110 D
b111 )
b111 /
b101 (
b101 -
b101 8
b101 @
b1 '
b1 ,
b1 7
b1 ?
b10101 +
#500000
0$
b1100 3
b1100 :
b1 "
b1 0
b1 2
b1 =
b10 9
b10 A
b1100 <
b1 1
b1 B
b1 D
b110 )
b110 /
b1010 (
b1010 -
b1010 8
b1010 @
b1011 '
b1011 ,
b1011 7
b1011 ?
b10110 +
#510000
1.
b100 3
b100 :
b100 "
b100 0
b100 2
b100 =
b1 9
b1 A
b100 <
b101 1
b101 B
b101 D
b1 )
b1 /
b1 (
b1 -
b1 8
b1 @
b101 '
b101 ,
b101 7
b101 ?
b10111 +
#520000
1$
b1101 "
b1101 0
b1101 2
b1101 =
0.
0%
b1 3
b1 :
b11 9
b11 A
05
b1 <
b1101 1
b1101 B
b1101 D
b111 )
b111 /
b1100 (
b1100 -
b1100 8
b1100 @
b10 '
b10 ,
b10 7
b10 ?
b11000 +
#530000
0$
b1110 3
b1110 :
1!
b0 "
b0 0
b0 2
b0 =
b1110 <
b0 1
b0 B
b0 D
b1000 (
b1000 -
b1000 8
b1000 @
b1111 '
b1111 ,
b1111 7
b1111 ?
b11001 +
#540000
1$
0!
b1110 "
b1110 0
b1110 2
b1110 =
1.
b11 )
b11 /
b1100 (
b1100 -
b1100 8
b1100 @
b11010 +
#550000
0$
1#
1%
b10 "
b10 0
b10 2
b10 =
14
15
b10 3
b10 :
b0 9
b0 A
b10010 <
b1001 1
b1001 B
b1001 D
b0 )
b0 /
b1001 (
b1001 -
b1001 8
b1001 @
b1001 '
b1001 ,
b1001 7
b1001 ?
b11011 +
#560000
0#
b110 "
b110 0
b110 2
b110 =
0.
0%
b1000 3
b1000 :
b10 9
b10 A
05
b1000 <
b110 1
b110 B
b110 D
b110 )
b110 /
b1 (
b1 -
b1 8
b1 @
b111 '
b111 ,
b111 7
b111 ?
b11100 +
#570000
1$
1.
b1110 3
b1110 :
b1110 "
b1110 0
b1110 2
b1110 =
b0 9
b0 A
04
b1110 <
b0 1
b0 B
b0 D
b0 )
b0 /
b10 (
b10 -
b10 8
b10 @
b1100 '
b1100 ,
b1100 7
b1100 ?
b11101 +
#580000
1$
1#
b1000 "
b1000 0
b1000 2
b1000 =
14
0%
b1000 3
b1000 :
b10 9
b10 A
05
b1000 <
b1010 1
b1010 B
b1010 D
b10 )
b10 /
b1101 (
b1101 -
b1101 8
b1101 @
b111 '
b111 ,
b111 7
b111 ?
b11110 +
#590000
0$
b1 "
b1 0
b1 2
b1 =
0#
b1 3
b1 :
b1 9
b1 A
04
b1 <
b1111 1
b1111 B
b1111 D
b1 )
b1 /
b1110 '
b1110 ,
b1110 7
b1110 ?
b11111 +
#600000
1$
b1111 "
b1111 0
b1111 2
b1111 =
0.
b1100 3
b1100 :
b1100 <
b101 )
b101 /
b11 (
b11 -
b11 8
b11 @
b1111 '
b1111 ,
b1111 7
b1111 ?
b100000 +
#610000
1%
1.
b1101 3
b1101 :
b1101 "
b1101 0
b1101 2
b1101 =
15
b11101 <
b1011 1
b1011 B
b1011 D
b1 )
b1 /
b1011 (
b1011 -
b1011 8
b1011 @
b1000 '
b1000 ,
b1000 7
b1000 ?
b100001 +
#620000
1$
b1001 "
b1001 0
b1001 2
b1001 =
1%
b1001 3
b1001 :
b0 9
b0 A
15
b11001 <
b1010 1
b1010 B
b1010 D
b0 )
b0 /
b1010 (
b1010 -
b1010 8
b1010 @
b1111 '
b1111 ,
b1111 7
b1111 ?
b100010 +
#630000
0$
0%
b110 "
b110 0
b110 2
b110 =
0.
b100 3
b100 :
b10100 <
b110 1
b110 B
b110 D
b100 )
b100 /
b1110 (
b1110 -
b1110 8
b1110 @
b110 '
b110 ,
b110 7
b110 ?
b100011 +
#640000
1$
0!
1.
05
b1001 3
b1001 :
b1001 "
b1001 0
b1001 2
b1001 =
b11 9
b11 A
b1001 <
b101 1
b101 B
b101 D
b11 )
b11 /
b110 (
b110 -
b110 8
b110 @
b1010 '
b1010 ,
b1010 7
b1010 ?
b100100 +
#650000
0$
b10 "
b10 0
b10 2
b10 =
b10 3
b10 :
b10 <
b1100 1
b1100 B
b1100 D
b1111 (
b1111 -
b1111 8
b1111 @
b11 '
b11 ,
b11 7
b11 ?
b100101 +
#660000
1!
b0 "
b0 0
b0 2
b0 =
0.
b1110 3
b1110 :
b1110 <
b0 1
b0 B
b0 D
b111 )
b111 /
b100 (
b100 -
b100 8
b100 @
b1111 '
b1111 ,
b1111 7
b1111 ?
b100110 +
